ursctl/__init__.py
ursctl/__main__.py
ursctl/ursctl.py
ursctl-0.1.2.dist-info/AUTHORS.rst
ursctl-0.1.2.dist-info/LICENSE
ursctl-0.1.2.dist-info/METADATA
ursctl-0.1.2.dist-info/WHEEL
ursctl-0.1.2.dist-info/entry_points.txt
ursctl-0.1.2.dist-info/top_level.txt
ursctl-0.1.2.dist-info/RECORD
