Metadata-Version: 2.1
Name: ursctl
Version: 0.1.2
Summary: Cisco Umbrella Roaming Security module for AnyConnect control utility
Home-page: https://github.com/jasmas/ursctl
Author: Jason Masker
Author-email: masker@post.harvard.edu
License: MIT
Platform: UNKNOWN
Classifier: Programming Language :: Python :: 3
Classifier: License :: OSI Approved :: MIT License
Classifier: Operating System :: OS Independent
